strnd/__init__.py
strnd/core.py
strnd/io.py
strnd/test.py
strnd-0.1.0.dist-info/METADATA
strnd-0.1.0.dist-info/WHEEL
strnd-0.1.0.dist-info/top_level.txt
strnd-0.1.0.dist-info/RECORD
