Metadata-Version: 2.4
Name: strnd
Version: 0.1.0
Summary: STRND: Graph reconstruction via Node2Vec (pecanpy) + UMAP
Author: Your Name
License: MIT
Keywords: graphs,embedding,node2vec,umap,networkx,representation learning
Requires-Python: >=3.9
Requires-Dist: matplotlib==3.5.1
Requires-Dist: networkx<3.0
Requires-Dist: numpy<2,>=1.22.4
Requires-Dist: pandas<2.0.0
Requires-Dist: pecanpy==2.0.9
Requires-Dist: proxigraph==0.1.2
Requires-Dist: PointQuality
Requires-Dist: umap-learn==0.5.5
Provides-Extra: pyg
Requires-Dist: torch>=2.0; extra == "pyg"
